pypararius/__init__.py
pypararius/listing.py
pypararius/pararius.py
pypararius/parser.py
pypararius-2.0.0.dist-info/METADATA
pypararius-2.0.0.dist-info/WHEEL
pypararius-2.0.0.dist-info/RECORD
