Metadata-Version: 2.4
Name: pypararius
Version: 2.0.0
Summary: Python API wrapper for Pararius.com real estate listings
Requires-Python: >=3.10
Requires-Dist: httpx>=0.27.0
Provides-Extra: dev
Requires-Dist: pytest-asyncio>=0.23.0; extra == 'dev'
Requires-Dist: pytest>=8.0.0; extra == 'dev'
